pygisty/__init__.py
pygisty/main.py
pygisty/options.py
pygisty/gisty/__init__.py
pygisty/gisty/headless.py
pygisty/gisty/post.py
pygisty/gisty/version.py
pygisty-0.0.7.dist-info/LICENCE
pygisty-0.0.7.dist-info/METADATA
pygisty-0.0.7.dist-info/WHEEL
pygisty-0.0.7.dist-info/entry_points.txt
pygisty-0.0.7.dist-info/top_level.txt
pygisty-0.0.7.dist-info/RECORD
