Metadata-Version: 2.1
Name: pygisty
Version: 0.0.7
Summary: Bad GitHub Gist client
Home-page: https://github.com/BlyatManGopnik/pygisty
Author: BlyatManGopnik
Author-email: emailforsurveys420@gmail.com
License: UNKNOWN
Platform: UNKNOWN
Classifier: Programming Language :: Python :: 3
Classifier: License :: OSI Approved :: MIT License
Classifier: Operating System :: OS Independent
Requires-Python: >=3.6
Requires-Dist: requests
Requires-Dist: appdirs
